{
  "$schema": "https://developer.microsoft.com/json-schemas/fabric/item/report/definition/visualContainer/2.4.0/schema.json",
  "name": "c6a987be869b83b365bb",
  "position": {
    "x": 328.94963015146175,
    "y": 71.416696019725251,
    "z": 11003,
    "height": 157.98238816484678,
    "width": 307.3082071151814,
    "tabOrder": 9000
  },
  "visual": {
    "visualType": "htmlContent443BE3AD55E043BF878BED274D3A6855",
    "query": {
      "queryState": {
        "content": {
          "projections": [
            {
              "field": {
                "Measure": {
                  "Expression": {
                    "SourceRef": {
                      "Entity": "Medidas"
                    }
                  },
                  "Property": "crd_Var % Absoluta"
                }
              },
              "queryRef": "Medidas.crd_Var % Absoluta",
              "nativeQueryRef": "crd_Var % Absoluta"
            }
          ]
        }
      }
    },
    "visualContainerObjects": {
      "padding": [
        {
          "properties": {
            "left": {
              "expr": {
                "Literal": {
                  "Value": "0D"
                }
              }
            },
            "right": {
              "expr": {
                "Literal": {
                  "Value": "0D"
                }
              }
            }
          }
        }
      ],
      "background": [
        {
          "properties": {
            "show": {
              "expr": {
                "Literal": {
                  "Value": "false"
                }
              }
            }
          }
        }
      ]
    },
    "drillFilterOtherVisuals": true
  }
}